{
  "classification_report": {
    "Culture": {
      "precision": 0.41935483870967744,
      "recall": 0.35135135135135137,
      "f1-score": 0.38235294117647056,
      "support": 111.0
    },
    "Tech": {
      "precision": 0.759493670886076,
      "recall": 0.5882352941176471,
      "f1-score": 0.6629834254143646,
      "support": 102.0
    },
    "Education": {
      "precision": 0.3595505617977528,
      "recall": 0.3368421052631579,
      "f1-score": 0.34782608695652173,
      "support": 95.0
    },
    "Family": {
      "precision": 0.5434782608695652,
      "recall": 0.4166666666666667,
      "f1-score": 0.4716981132075472,
      "support": 120.0
    },
    "Health": {
      "precision": 0.6170212765957447,
      "recall": 0.5576923076923077,
      "f1-score": 0.5858585858585859,
      "support": 104.0
    },
    "Politics": {
      "precision": 0.5128205128205128,
      "recall": 0.37383177570093457,
      "f1-score": 0.43243243243243246,
      "support": 107.0
    },
    "Sports": {
      "precision": 0.7419354838709677,
      "recall": 0.5542168674698795,
      "f1-score": 0.6344827586206897,
      "support": 83.0
    },
    "Entertainment": {
      "precision": 0.46218487394957986,
      "recall": 0.5188679245283019,
      "f1-score": 0.4888888888888889,
      "support": 106.0
    },
    "Business": {
      "precision": 0.2875,
      "recall": 0.27058823529411763,
      "f1-score": 0.2787878787878788,
      "support": 85.0
    },
    "Science": {
      "precision": 0.484375,
      "recall": 0.3563218390804598,
      "f1-score": 0.4105960264900662,
      "support": 87.0
    },
    "micro avg": {
      "precision": 0.5105882352941177,
      "recall": 0.434,
      "f1-score": 0.46918918918918917,
      "support": 1000.0
    },
    "macro avg": {
      "precision": 0.5187714479499876,
      "recall": 0.4324614367164824,
      "f1-score": 0.4695907137833447,
      "support": 1000.0
    },
    "weighted avg": {
      "precision": 0.5195838106399864,
      "recall": 0.434,
      "f1-score": 0.4708154160975368,
      "support": 1000.0
    }
  },
  "accuracy": 0.434,
  "confusion_matrix": [
    [
      39,
      0,
      5,
      11,
      9,
      11,
      4,
      14,
      3,
      5
    ],
    [
      3,
      60,
      3,
      5,
      2,
      2,
      0,
      2,
      7,
      3
    ],
    [
      7,
      4,
      32,
      5,
      3,
      5,
      2,
      5,
      14,
      10
    ],
    [
      5,
      1,
      4,
      50,
      3,
      2,
      1,
      2,
      7,
      0
    ],
    [
      2,
      1,
      5,
      6,
      58,
      2,
      1,
      5,
      4,
      3
    ],
    [
      13,
      1,
      8,
      3,
      5,
      40,
      0,
      11,
      8,
      2
    ],
    [
      3,
      3,
      1,
      0,
      2,
      1,
      46,
      10,
      2,
      4
    ],
    [
      12,
      2,
      3,
      5,
      3,
      6,
      5,
      55,
      7,
      3
    ],
    [
      5,
      5,
      11,
      4,
      3,
      7,
      2,
      8,
      23,
      3
    ],
    [
      4,
      2,
      17,
      3,
      6,
      2,
      1,
      7,
      5,
      31
    ]
  ],
  "labels": [
    "Culture",
    "Tech",
    "Education",
    "Family",
    "Health",
    "Politics",
    "Sports",
    "Entertainment",
    "Business",
    "Science"
  ]
}