{
  "prompt_lengths": {
    "mean": 860.193,
    "min": 489,
    "max": 1258,
    "std": 136.0363765725918,
    "values": [
      731,
      677,
      717,
      810,
      808,
      703,
      840,
      1030,
      1076,
      745,
      1056,
      1028,
      1003,
      957,
      936,
      933,
      856,
      748,
      950,
      754,
      974,
      1225,
      628,
      926,
      649,
      720,
      541,
      690,
      960,
      1008,
      748,
      657,
      951,
      818,
      953,
      711,
      769,
      748,
      672,
      774,
      854,
      891,
      889,
      1017,
      987,
      675,
      731,
      967,
      983,
      952,
      976,
      673,
      892,
      996,
      735,
      908,
      903,
      917,
      1019,
      951,
      978,
      622,
      1023,
      981,
      670,
      923,
      766,
      1082,
      719,
      842,
      637,
      939,
      827,
      674,
      1021,
      891,
      928,
      678,
      893,
      935,
      935,
      612,
      949,
      822,
      864,
      957,
      1114,
      861,
      737,
      870,
      816,
      931,
      825,
      753,
      1032,
      848,
      837,
      882,
      986,
      786,
      710,
      733,
      812,
      778,
      652,
      613,
      704,
      761,
      1007,
      642,
      1123,
      721,
      942,
      1034,
      647,
      803,
      893,
      885,
      764,
      930,
      1135,
      998,
      710,
      862,
      1006,
      920,
      850,
      824,
      683,
      999,
      843,
      1048,
      695,
      786,
      865,
      604,
      716,
      933,
      744,
      977,
      1080,
      969,
      525,
      928,
      847,
      946,
      743,
      901,
      626,
      921,
      750,
      940,
      842,
      1114,
      1046,
      763,
      989,
      747,
      834,
      667,
      697,
      900,
      864,
      773,
      838,
      819,
      657,
      1067,
      873,
      1048,
      1019,
      950,
      759,
      791,
      599,
      908,
      838,
      877,
      754,
      790,
      997,
      783,
      844,
      859,
      874,
      674,
      833,
      709,
      919,
      897,
      827,
      1013,
      1019,
      704,
      743,
      619,
      905,
      680,
      671,
      800,
      971,
      875,
      1011,
      1041,
      810,
      855,
      813,
      852,
      829,
      587,
      829,
      845,
      667,
      1068,
      932,
      764,
      839,
      997,
      765,
      986,
      755,
      1083,
      806,
      1029,
      791,
      1068,
      831,
      768,
      836,
      879,
      893,
      545,
      939,
      932,
      760,
      863,
      764,
      960,
      1084,
      832,
      1023,
      1082,
      752,
      990,
      972,
      1017,
      1071,
      792,
      865,
      940,
      714,
      925,
      901,
      887,
      938,
      910,
      839,
      844,
      685,
      637,
      1026,
      867,
      667,
      831,
      982,
      886,
      969,
      630,
      924,
      732,
      734,
      920,
      848,
      812,
      1025,
      931,
      730,
      779,
      740,
      788,
      837,
      734,
      903,
      749,
      636,
      725,
      880,
      610,
      804,
      1108,
      783,
      1037,
      749,
      984,
      759,
      719,
      826,
      915,
      869,
      971,
      998,
      1046,
      782,
      1028,
      591,
      769,
      967,
      1000,
      876,
      987,
      900,
      671,
      925,
      993,
      849,
      696,
      676,
      1017,
      803,
      926,
      953,
      668,
      881,
      937,
      832,
      863,
      809,
      1073,
      854,
      731,
      847,
      993,
      1012,
      966,
      673,
      1040,
      768,
      815,
      816,
      736,
      941,
      736,
      1013,
      554,
      661,
      784,
      751,
      913,
      683,
      867,
      859,
      809,
      828,
      997,
      1008,
      897,
      1002,
      652,
      518,
      643,
      913,
      983,
      987,
      964,
      889,
      982,
      917,
      796,
      778,
      751,
      672,
      922,
      900,
      663,
      795,
      1000,
      518,
      1159,
      799,
      821,
      786,
      984,
      1111,
      836,
      773,
      621,
      819,
      832,
      710,
      938,
      1033,
      903,
      689,
      684,
      1011,
      569,
      564,
      1005,
      766,
      1073,
      863,
      862,
      771,
      1108,
      866,
      807,
      702,
      680,
      847,
      899,
      928,
      829,
      981,
      908,
      790,
      782,
      804,
      865,
      657,
      1145,
      879,
      909,
      832,
      956,
      1106,
      946,
      594,
      1067,
      845,
      992,
      912,
      1041,
      966,
      1132,
      908,
      841,
      792,
      655,
      716,
      810,
      686,
      1056,
      861,
      893,
      736,
      1077,
      792,
      892,
      984,
      679,
      879,
      1101,
      977,
      890,
      967,
      1037,
      809,
      745,
      904,
      931,
      912,
      1106,
      991,
      988,
      841,
      826,
      896,
      711,
      932,
      880,
      522,
      882,
      1135,
      912,
      1051,
      923,
      895,
      621,
      917,
      731,
      606,
      870,
      991,
      859,
      750,
      868,
      801,
      823,
      809,
      991,
      768,
      1078,
      1010,
      970,
      1009,
      690,
      899,
      889,
      937,
      843,
      898,
      754,
      969,
      933,
      1127,
      620,
      977,
      978,
      755,
      764,
      802,
      951,
      644,
      803,
      782,
      907,
      888,
      859,
      744,
      915,
      931,
      758,
      772,
      985,
      857,
      868,
      919,
      939,
      643,
      956,
      840,
      908,
      1032,
      1011,
      627,
      815,
      727,
      902,
      865,
      769,
      967,
      787,
      958,
      1019,
      792,
      787,
      859,
      641,
      759,
      835,
      1008,
      980,
      790,
      851,
      644,
      929,
      579,
      930,
      840,
      606,
      967,
      987,
      880,
      773,
      850,
      765,
      974,
      695,
      789,
      893,
      719,
      940,
      874,
      848,
      1032,
      1069,
      876,
      611,
      970,
      937,
      513,
      602,
      959,
      868,
      768,
      885,
      956,
      1001,
      943,
      536,
      692,
      840,
      794,
      896,
      617,
      912,
      817,
      687,
      955,
      991,
      1096,
      1065,
      1036,
      913,
      969,
      541,
      954,
      827,
      1185,
      737,
      967,
      783,
      991,
      924,
      970,
      806,
      990,
      648,
      601,
      895,
      647,
      937,
      965,
      696,
      840,
      635,
      1103,
      499,
      832,
      773,
      802,
      995,
      1152,
      837,
      844,
      774,
      799,
      874,
      963,
      908,
      621,
      942,
      858,
      679,
      917,
      1030,
      770,
      1050,
      850,
      820,
      861,
      935,
      887,
      893,
      830,
      759,
      739,
      983,
      966,
      923,
      760,
      893,
      859,
      824,
      857,
      789,
      830,
      966,
      916,
      1091,
      662,
      1042,
      1073,
      1029,
      937,
      800,
      809,
      876,
      598,
      860,
      648,
      976,
      858,
      909,
      1043,
      743,
      864,
      489,
      1048,
      896,
      981,
      881,
      638,
      807,
      985,
      915,
      888,
      1089,
      890,
      1004,
      1127,
      993,
      534,
      1015,
      813,
      862,
      907,
      971,
      878,
      907,
      762,
      1075,
      619,
      814,
      959,
      722,
      761,
      632,
      866,
      691,
      675,
      938,
      1233,
      794,
      638,
      968,
      759,
      957,
      898,
      1125,
      909,
      922,
      1063,
      1132,
      960,
      998,
      730,
      941,
      745,
      908,
      942,
      955,
      866,
      823,
      977,
      700,
      916,
      1025,
      938,
      870,
      992,
      1065,
      998,
      670,
      940,
      811,
      809,
      776,
      833,
      1048,
      1069,
      799,
      979,
      648,
      817,
      1086,
      962,
      1037,
      780,
      1134,
      1122,
      1000,
      936,
      789,
      810,
      831,
      579,
      879,
      969,
      569,
      1101,
      853,
      735,
      795,
      1016,
      995,
      821,
      865,
      669,
      943,
      750,
      1117,
      813,
      820,
      837,
      941,
      722,
      930,
      822,
      925,
      795,
      544,
      970,
      865,
      762,
      708,
      937,
      948,
      898,
      869,
      790,
      768,
      1119,
      882,
      731,
      1079,
      824,
      1063,
      745,
      813,
      797,
      851,
      833,
      723,
      661,
      810,
      533,
      896,
      869,
      1258,
      953,
      738,
      1053,
      868,
      888,
      929,
      736,
      1075,
      744,
      809,
      1081,
      1047,
      1043,
      965,
      966,
      587,
      1020,
      760,
      724,
      708,
      930,
      789,
      971,
      851,
      741,
      618,
      603,
      800,
      970,
      1015,
      789,
      1022,
      953,
      954,
      1048,
      1142,
      823,
      823,
      932,
      947,
      956,
      841,
      920,
      904,
      945,
      901,
      981,
      979,
      854,
      865,
      993,
      677,
      569,
      1111,
      704,
      758,
      848,
      550,
      863,
      616,
      667,
      858,
      598,
      806,
      922,
      895,
      681,
      789,
      795,
      952,
      764,
      1074,
      943,
      917,
      851,
      1091,
      1012,
      771,
      924,
      893,
      755,
      587,
      840,
      933,
      836,
      996,
      953,
      655,
      925,
      884,
      915,
      517,
      798,
      760,
      1019,
      817,
      753,
      849,
      818,
      909,
      797,
      933,
      715,
      711,
      707,
      929,
      753,
      870,
      983,
      774,
      923,
      999,
      854,
      793,
      943,
      922,
      697,
      946,
      862,
      1015,
      835,
      951,
      821,
      959,
      1059,
      1030,
      610,
      1118,
      821,
      743,
      814,
      777,
      911,
      833,
      884,
      821,
      686,
      1041,
      878,
      998,
      971,
      875,
      853,
      783,
      1072,
      1023,
      986,
      763,
      965,
      1164,
      507,
      770,
      788,
      802,
      944,
      908,
      840,
      775,
      955,
      897,
      728,
      920,
      705,
      1033,
      763,
      887,
      878,
      718,
      760,
      825
    ]
  },
  "input_lengths": {
    "mean": 16.11,
    "min": 2,
    "max": 44,
    "std": 8.291073513122411,
    "values": [
      25,
      5,
      17,
      10,
      8,
      4,
      22,
      21,
      32,
      5,
      33,
      15,
      33,
      23,
      16,
      5,
      29,
      11,
      20,
      15,
      15,
      14,
      5,
      9,
      13,
      14,
      4,
      15,
      17,
      28,
      15,
      23,
      30,
      17,
      24,
      7,
      10,
      8,
      6,
      7,
      14,
      10,
      18,
      22,
      13,
      5,
      16,
      34,
      25,
      12,
      4,
      6,
      19,
      12,
      9,
      17,
      9,
      17,
      18,
      9,
      23,
      11,
      22,
      26,
      3,
      18,
      13,
      19,
      5,
      25,
      17,
      8,
      7,
      3,
      17,
      7,
      24,
      15,
      15,
      10,
      23,
      6,
      28,
      3,
      15,
      18,
      27,
      14,
      19,
      11,
      7,
      10,
      9,
      11,
      19,
      15,
      9,
      12,
      21,
      31,
      8,
      4,
      4,
      6,
      6,
      22,
      17,
      8,
      21,
      6,
      25,
      21,
      15,
      26,
      10,
      6,
      16,
      8,
      5,
      23,
      13,
      21,
      9,
      12,
      25,
      26,
      5,
      21,
      4,
      23,
      9,
      24,
      14,
      8,
      7,
      14,
      5,
      19,
      18,
      21,
      28,
      21,
      7,
      18,
      13,
      3,
      11,
      19,
      4,
      18,
      11,
      6,
      23,
      29,
      19,
      13,
      22,
      8,
      12,
      7,
      4,
      13,
      30,
      7,
      23,
      24,
      11,
      29,
      12,
      19,
      5,
      24,
      5,
      7,
      24,
      20,
      28,
      12,
      22,
      14,
      10,
      6,
      10,
      31,
      20,
      17,
      7,
      17,
      21,
      25,
      9,
      10,
      26,
      8,
      38,
      5,
      28,
      8,
      5,
      25,
      31,
      15,
      22,
      24,
      33,
      42,
      13,
      8,
      10,
      14,
      17,
      24,
      31,
      21,
      12,
      27,
      17,
      11,
      6,
      10,
      42,
      26,
      29,
      21,
      16,
      18,
      12,
      18,
      16,
      18,
      23,
      10,
      19,
      24,
      6,
      27,
      16,
      24,
      31,
      14,
      18,
      31,
      8,
      21,
      28,
      28,
      19,
      23,
      25,
      15,
      19,
      20,
      21,
      15,
      20,
      22,
      13,
      4,
      18,
      6,
      7,
      11,
      27,
      18,
      44,
      10,
      28,
      8,
      24,
      6,
      20,
      10,
      4,
      5,
      33,
      17,
      3,
      25,
      9,
      29,
      9,
      9,
      23,
      7,
      33,
      3,
      5,
      8,
      12,
      20,
      8,
      17,
      24,
      13,
      6,
      8,
      15,
      29,
      16,
      16,
      7,
      16,
      23,
      19,
      6,
      7,
      13,
      20,
      22,
      30,
      5,
      7,
      8,
      25,
      6,
      31,
      17,
      14,
      6,
      26,
      23,
      13,
      8,
      18,
      8,
      31,
      21,
      27,
      16,
      26,
      21,
      21,
      19,
      16,
      5,
      14,
      16,
      11,
      24,
      20,
      21,
      16,
      16,
      4,
      11,
      13,
      30,
      15,
      3,
      6,
      22,
      6,
      26,
      4,
      9,
      36,
      12,
      7,
      13,
      5,
      24,
      32,
      15,
      8,
      28,
      16,
      17,
      5,
      16,
      19,
      9,
      18,
      10,
      4,
      12,
      7,
      13,
      13,
      4,
      12,
      7,
      27,
      27,
      20,
      21,
      6,
      15,
      29,
      12,
      22,
      15,
      9,
      25,
      4,
      20,
      28,
      4,
      13,
      16,
      23,
      6,
      10,
      10,
      25,
      11,
      5,
      6,
      8,
      20,
      6,
      14,
      14,
      6,
      10,
      10,
      12,
      23,
      21,
      11,
      34,
      13,
      12,
      13,
      31,
      35,
      22,
      5,
      25,
      23,
      10,
      24,
      23,
      20,
      15,
      15,
      27,
      15,
      3,
      10,
      32,
      4,
      16,
      7,
      17,
      28,
      33,
      26,
      8,
      20,
      8,
      15,
      25,
      26,
      30,
      5,
      17,
      17,
      6,
      27,
      3,
      14,
      14,
      17,
      11,
      16,
      18,
      10,
      5,
      18,
      19,
      6,
      27,
      27,
      14,
      26,
      32,
      6,
      30,
      18,
      9,
      9,
      14,
      18,
      13,
      24,
      13,
      22,
      20,
      7,
      3,
      25,
      14,
      16,
      23,
      18,
      3,
      7,
      16,
      35,
      6,
      17,
      12,
      14,
      19,
      23,
      7,
      21,
      14,
      4,
      16,
      11,
      25,
      13,
      12,
      6,
      18,
      22,
      8,
      19,
      24,
      20,
      34,
      17,
      26,
      18,
      14,
      31,
      20,
      8,
      30,
      6,
      23,
      15,
      17,
      5,
      8,
      14,
      17,
      12,
      8,
      10,
      17,
      28,
      13,
      22,
      10,
      30,
      7,
      23,
      12,
      16,
      28,
      24,
      25,
      12,
      15,
      5,
      28,
      11,
      7,
      29,
      16,
      25,
      7,
      5,
      8,
      12,
      7,
      14,
      6,
      8,
      18,
      16,
      19,
      19,
      23,
      17,
      5,
      18,
      11,
      3,
      11,
      21,
      26,
      6,
      25,
      8,
      18,
      27,
      3,
      18,
      4,
      10,
      25,
      5,
      32,
      15,
      14,
      14,
      25,
      28,
      20,
      20,
      17,
      7,
      7,
      19,
      11,
      22,
      5,
      18,
      18,
      25,
      15,
      19,
      13,
      4,
      9,
      25,
      27,
      8,
      16,
      37,
      25,
      22,
      10,
      21,
      6,
      10,
      27,
      5,
      12,
      23,
      25,
      17,
      16,
      10,
      23,
      22,
      35,
      23,
      16,
      7,
      13,
      30,
      19,
      28,
      19,
      15,
      6,
      15,
      16,
      28,
      15,
      21,
      15,
      4,
      19,
      11,
      28,
      20,
      10,
      10,
      35,
      6,
      5,
      18,
      22,
      15,
      20,
      5,
      17,
      29,
      32,
      5,
      12,
      20,
      15,
      5,
      28,
      22,
      6,
      7,
      23,
      5,
      16,
      22,
      2,
      20,
      16,
      21,
      13,
      11,
      11,
      28,
      26,
      26,
      12,
      7,
      24,
      26,
      29,
      6,
      19,
      23,
      14,
      5,
      23,
      9,
      19,
      7,
      20,
      10,
      5,
      28,
      13,
      19,
      20,
      14,
      4,
      23,
      8,
      20,
      22,
      9,
      5,
      7,
      23,
      28,
      16,
      17,
      22,
      22,
      32,
      8,
      10,
      23,
      20,
      13,
      23,
      20,
      24,
      11,
      19,
      21,
      11,
      33,
      23,
      6,
      11,
      25,
      28,
      28,
      6,
      8,
      21,
      4,
      5,
      20,
      17,
      20,
      11,
      17,
      15,
      21,
      12,
      14,
      4,
      8,
      22,
      20,
      10,
      18,
      7,
      20,
      19,
      18,
      24,
      33,
      29,
      34,
      14,
      5,
      28,
      27,
      15,
      6,
      17,
      5,
      13,
      31,
      24,
      9,
      9,
      9,
      32,
      5,
      31,
      31,
      7,
      34,
      24,
      28,
      5,
      32,
      14,
      15,
      9,
      16,
      25,
      7,
      12,
      23,
      6,
      3,
      10,
      14,
      22,
      9,
      22,
      29,
      21,
      13,
      22,
      17,
      26,
      4,
      5,
      11,
      30,
      17,
      6,
      32,
      9,
      5,
      12,
      15,
      28,
      8,
      11,
      24,
      20,
      27,
      26,
      12,
      8,
      23,
      20,
      16,
      6,
      12,
      8,
      9,
      21,
      9,
      10,
      9,
      20,
      13,
      18,
      4,
      34,
      15,
      12,
      14,
      24,
      16,
      9,
      17,
      25,
      21,
      19,
      29,
      23,
      4,
      7,
      12,
      25,
      16,
      15,
      18,
      24,
      8,
      16,
      4,
      14,
      12,
      7,
      21,
      5,
      6,
      21,
      7,
      11,
      26,
      33,
      10,
      14,
      28,
      16,
      8,
      13,
      12,
      18,
      7,
      28,
      13,
      15,
      27,
      21,
      21,
      21,
      4,
      25,
      7,
      28,
      17,
      13,
      14,
      15,
      15,
      4,
      15,
      12,
      16,
      22,
      7,
      8,
      29,
      14,
      18,
      4,
      32,
      11,
      15,
      5,
      8,
      13,
      27,
      26,
      21,
      28,
      15,
      19,
      18,
      16,
      7,
      14,
      4,
      15,
      3,
      21,
      13,
      13,
      18,
      28,
      5,
      21,
      8,
      5,
      19,
      27,
      12,
      9,
      6,
      24,
      5,
      33,
      6,
      27,
      12,
      26,
      13,
      11,
      13,
      19,
      25,
      6,
      26,
      24,
      8,
      3,
      17,
      21,
      8,
      24,
      17,
      3,
      30,
      12,
      8,
      19,
      7,
      28,
      11,
      9,
      26,
      8,
      6,
      7
    ]
  },
  "shots_lengths": {
    "mean": 660.633,
    "min": 333,
    "max": 1017,
    "std": 118.37651925529826,
    "values": [
      556,
      509,
      528,
      605,
      630,
      527,
      642,
      801,
      846,
      573,
      826,
      815,
      782,
      741,
      732,
      725,
      645,
      581,
      735,
      592,
      769,
      990,
      462,
      716,
      494,
      541,
      399,
      536,
      743,
      788,
      566,
      488,
      731,
      622,
      750,
      542,
      587,
      580,
      518,
      594,
      645,
      695,
      656,
      797,
      757,
      474,
      553,
      745,
      771,
      739,
      771,
      492,
      677,
      786,
      559,
      712,
      685,
      712,
      791,
      749,
      766,
      452,
      809,
      757,
      502,
      713,
      588,
      851,
      553,
      645,
      466,
      726,
      595,
      502,
      786,
      688,
      723,
      495,
      686,
      700,
      725,
      415,
      748,
      630,
      651,
      752,
      871,
      670,
      554,
      683,
      618,
      698,
      618,
      567,
      807,
      656,
      651,
      685,
      793,
      603,
      543,
      550,
      623,
      577,
      472,
      453,
      512,
      572,
      793,
      470,
      906,
      552,
      734,
      814,
      476,
      613,
      684,
      683,
      580,
      722,
      915,
      763,
      539,
      670,
      775,
      715,
      651,
      634,
      499,
      762,
      654,
      814,
      522,
      612,
      683,
      448,
      525,
      730,
      561,
      772,
      863,
      753,
      383,
      727,
      643,
      738,
      558,
      695,
      479,
      716,
      562,
      726,
      648,
      859,
      812,
      579,
      778,
      551,
      637,
      477,
      508,
      693,
      668,
      586,
      638,
      621,
      483,
      839,
      667,
      828,
      796,
      735,
      582,
      606,
      440,
      697,
      647,
      664,
      577,
      604,
      787,
      605,
      642,
      647,
      670,
      506,
      626,
      529,
      699,
      688,
      636,
      805,
      780,
      507,
      560,
      448,
      693,
      484,
      493,
      599,
      757,
      682,
      791,
      810,
      616,
      641,
      615,
      664,
      607,
      432,
      606,
      647,
      486,
      837,
      725,
      581,
      649,
      791,
      592,
      792,
      561,
      865,
      611,
      808,
      589,
      843,
      643,
      583,
      631,
      684,
      684,
      389,
      738,
      740,
      564,
      671,
      560,
      749,
      839,
      645,
      794,
      847,
      557,
      782,
      751,
      799,
      852,
      591,
      661,
      731,
      538,
      710,
      695,
      673,
      720,
      680,
      634,
      649,
      528,
      477,
      805,
      645,
      474,
      626,
      750,
      697,
      767,
      456,
      705,
      564,
      558,
      723,
      647,
      591,
      803,
      736,
      543,
      606,
      555,
      585,
      642,
      553,
      708,
      559,
      470,
      545,
      667,
      441,
      583,
      859,
      587,
      830,
      565,
      763,
      576,
      528,
      635,
      701,
      645,
      757,
      796,
      829,
      596,
      814,
      429,
      593,
      781,
      764,
      680,
      765,
      690,
      494,
      705,
      772,
      625,
      502,
      513,
      811,
      593,
      716,
      758,
      501,
      676,
      730,
      643,
      662,
      617,
      855,
      644,
      564,
      646,
      767,
      797,
      749,
      519,
      820,
      587,
      597,
      631,
      561,
      743,
      556,
      791,
      384,
      475,
      591,
      546,
      685,
      484,
      642,
      662,
      602,
      631,
      787,
      782,
      675,
      787,
      463,
      374,
      479,
      704,
      764,
      773,
      767,
      697,
      768,
      707,
      603,
      586,
      577,
      502,
      696,
      677,
      490,
      601,
      802,
      338,
      940,
      621,
      605,
      601,
      777,
      879,
      632,
      585,
      455,
      611,
      639,
      545,
      703,
      823,
      704,
      504,
      508,
      789,
      407,
      417,
      778,
      576,
      843,
      667,
      661,
      592,
      876,
      674,
      612,
      523,
      510,
      662,
      686,
      741,
      619,
      756,
      715,
      591,
      573,
      618,
      671,
      469,
      888,
      669,
      721,
      628,
      722,
      855,
      720,
      440,
      835,
      649,
      762,
      698,
      825,
      759,
      907,
      706,
      649,
      602,
      491,
      557,
      606,
      493,
      822,
      658,
      673,
      525,
      850,
      592,
      696,
      765,
      497,
      670,
      862,
      737,
      670,
      769,
      824,
      614,
      558,
      681,
      721,
      704,
      879,
      778,
      776,
      625,
      633,
      668,
      539,
      715,
      670,
      367,
      667,
      889,
      708,
      827,
      715,
      679,
      462,
      735,
      549,
      420,
      658,
      796,
      671,
      571,
      669,
      594,
      615,
      628,
      771,
      600,
      855,
      808,
      756,
      797,
      528,
      697,
      682,
      725,
      658,
      678,
      573,
      761,
      712,
      900,
      457,
      757,
      770,
      567,
      569,
      622,
      738,
      494,
      628,
      598,
      712,
      694,
      667,
      557,
      701,
      729,
      557,
      584,
      760,
      667,
      668,
      704,
      738,
      472,
      742,
      648,
      705,
      817,
      794,
      459,
      633,
      525,
      696,
      682,
      594,
      742,
      611,
      740,
      795,
      590,
      613,
      650,
      472,
      570,
      645,
      797,
      749,
      595,
      658,
      450,
      725,
      423,
      718,
      635,
      441,
      758,
      779,
      688,
      577,
      657,
      573,
      764,
      504,
      580,
      690,
      537,
      739,
      701,
      637,
      806,
      835,
      663,
      450,
      763,
      725,
      375,
      460,
      748,
      669,
      572,
      661,
      743,
      793,
      706,
      394,
      535,
      646,
      591,
      679,
      435,
      703,
      622,
      520,
      756,
      765,
      868,
      827,
      805,
      721,
      761,
      389,
      727,
      607,
      944,
      566,
      771,
      595,
      766,
      713,
      763,
      616,
      767,
      492,
      434,
      702,
      482,
      720,
      733,
      497,
      647,
      456,
      870,
      355,
      648,
      579,
      612,
      786,
      907,
      637,
      656,
      585,
      627,
      678,
      750,
      704,
      454,
      722,
      669,
      516,
      709,
      835,
      580,
      813,
      674,
      613,
      683,
      714,
      669,
      675,
      630,
      550,
      556,
      775,
      774,
      708,
      569,
      694,
      664,
      616,
      663,
      615,
      630,
      758,
      705,
      862,
      494,
      833,
      839,
      782,
      720,
      619,
      612,
      681,
      432,
      658,
      480,
      755,
      680,
      698,
      834,
      573,
      649,
      333,
      829,
      699,
      780,
      662,
      471,
      639,
      767,
      719,
      675,
      864,
      676,
      787,
      896,
      762,
      376,
      808,
      615,
      638,
      708,
      750,
      691,
      713,
      579,
      866,
      424,
      610,
      737,
      543,
      585,
      473,
      678,
      514,
      506,
      714,
      988,
      613,
      469,
      756,
      577,
      749,
      683,
      901,
      706,
      721,
      838,
      908,
      743,
      774,
      552,
      728,
      565,
      707,
      721,
      729,
      659,
      635,
      766,
      523,
      687,
      798,
      724,
      647,
      763,
      835,
      781,
      496,
      735,
      616,
      618,
      577,
      644,
      845,
      851,
      611,
      741,
      472,
      626,
      871,
      744,
      837,
      592,
      906,
      881,
      799,
      728,
      590,
      600,
      644,
      429,
      689,
      756,
      415,
      858,
      656,
      567,
      605,
      803,
      790,
      634,
      666,
      497,
      738,
      553,
      892,
      626,
      656,
      653,
      728,
      537,
      717,
      631,
      728,
      602,
      384,
      753,
      676,
      576,
      515,
      727,
      746,
      685,
      671,
      604,
      571,
      905,
      661,
      538,
      851,
      618,
      841,
      569,
      614,
      608,
      650,
      652,
      518,
      481,
      606,
      400,
      683,
      670,
      1017,
      741,
      561,
      827,
      659,
      695,
      743,
      552,
      850,
      575,
      618,
      869,
      817,
      806,
      755,
      736,
      409,
      806,
      587,
      543,
      517,
      730,
      607,
      765,
      660,
      542,
      470,
      449,
      616,
      745,
      792,
      599,
      801,
      737,
      755,
      823,
      911,
      633,
      631,
      717,
      737,
      757,
      642,
      706,
      688,
      725,
      702,
      781,
      759,
      659,
      670,
      755,
      516,
      434,
      891,
      528,
      542,
      662,
      387,
      658,
      456,
      480,
      632,
      440,
      593,
      703,
      684,
      515,
      605,
      590,
      742,
      588,
      843,
      728,
      712,
      668,
      873,
      785,
      587,
      709,
      692,
      556,
      425,
      615,
      707,
      645,
      783,
      728,
      496,
      714,
      702,
      731,
      379,
      615,
      565,
      790,
      609,
      582,
      645,
      632,
      702,
      604,
      724,
      542,
      527,
      506,
      724,
      580,
      669,
      762,
      589,
      722,
      773,
      660,
      620,
      735,
      708,
      518,
      748,
      671,
      799,
      659,
      740,
      635,
      741,
      848,
      801,
      450,
      887,
      611,
      556,
      635,
      582,
      705,
      648,
      675,
      625,
      531,
      798,
      680,
      773,
      749,
      665,
      652,
      605,
      857,
      803,
      778,
      566,
      732,
      923,
      348,
      580,
      596,
      599,
      737,
      704,
      639,
      598,
      732,
      705,
      543,
      715,
      519,
      813,
      571,
      703,
      675,
      537,
      567,
      611
    ]
  },
  "num_shots": {
    "mean": 40.119,
    "min": 23,
    "max": 53,
    "std": 5.3444212970161695,
    "values": [
      33,
      35,
      37,
      43,
      39,
      37,
      38,
      47,
      44,
      37,
      45,
      45,
      42,
      43,
      42,
      45,
      41,
      33,
      45,
      31,
      41,
      51,
      33,
      47,
      29,
      35,
      28,
      29,
      45,
      43,
      37,
      29,
      43,
      39,
      39,
      33,
      37,
      35,
      29,
      39,
      43,
      41,
      49,
      43,
      49,
      41,
      33,
      43,
      41,
      43,
      45,
      37,
      45,
      46,
      36,
      39,
      47,
      41,
      47,
      44,
      41,
      33,
      43,
      45,
      35,
      43,
      35,
      49,
      35,
      39,
      31,
      45,
      47,
      37,
      47,
      43,
      39,
      35,
      41,
      51,
      43,
      41,
      36,
      39,
      45,
      41,
      49,
      39,
      35,
      39,
      41,
      49,
      43,
      39,
      47,
      39,
      39,
      40,
      38,
      31,
      33,
      37,
      41,
      43,
      37,
      27,
      35,
      39,
      43,
      35,
      44,
      31,
      43,
      45,
      35,
      41,
      43,
      43,
      39,
      41,
      47,
      49,
      34,
      41,
      47,
      39,
      43,
      38,
      39,
      49,
      41,
      47,
      33,
      37,
      37,
      29,
      41,
      41,
      35,
      41,
      44,
      45,
      27,
      40,
      41,
      45,
      39,
      40,
      28,
      43,
      37,
      47,
      37,
      51,
      49,
      37,
      42,
      41,
      39,
      39,
      39,
      43,
      33,
      39,
      39,
      37,
      35,
      45,
      43,
      45,
      49,
      41,
      37,
      39,
      27,
      43,
      35,
      45,
      33,
      37,
      47,
      37,
      43,
      40,
      41,
      31,
      43,
      33,
      45,
      41,
      41,
      45,
      49,
      39,
      31,
      35,
      39,
      37,
      37,
      37,
      41,
      39,
      45,
      47,
      35,
      37,
      41,
      39,
      47,
      27,
      45,
      37,
      31,
      47,
      45,
      31,
      39,
      43,
      35,
      41,
      31,
      43,
      36,
      45,
      39,
      49,
      39,
      37,
      41,
      37,
      41,
      29,
      41,
      39,
      41,
      37,
      38,
      41,
      49,
      37,
      49,
      45,
      39,
      41,
      43,
      41,
      45,
      39,
      39,
      43,
      33,
      43,
      39,
      43,
      44,
      47,
      41,
      43,
      28,
      31,
      50,
      47,
      35,
      41,
      41,
      39,
      39,
      35,
      43,
      34,
      33,
      43,
      42,
      47,
      41,
      39,
      41,
      31,
      39,
      37,
      39,
      37,
      37,
      37,
      26,
      39,
      47,
      32,
      45,
      53,
      41,
      43,
      35,
      47,
      39,
      39,
      39,
      41,
      47,
      45,
      45,
      45,
      33,
      43,
      31,
      37,
      39,
      49,
      37,
      41,
      45,
      36,
      47,
      43,
      47,
      33,
      31,
      45,
      45,
      41,
      38,
      33,
      43,
      41,
      37,
      37,
      39,
      42,
      43,
      29,
      41,
      47,
      45,
      43,
      31,
      47,
      35,
      47,
      35,
      33,
      39,
      35,
      45,
      33,
      36,
      39,
      37,
      49,
      41,
      49,
      39,
      45,
      38,
      47,
      49,
      41,
      47,
      39,
      25,
      34,
      41,
      43,
      45,
      43,
      35,
      45,
      43,
      41,
      39,
      33,
      35,
      47,
      49,
      35,
      38,
      43,
      33,
      47,
      38,
      45,
      37,
      39,
      47,
      41,
      37,
      33,
      41,
      35,
      33,
      49,
      45,
      45,
      33,
      37,
      47,
      27,
      27,
      47,
      37,
      47,
      41,
      41,
      35,
      47,
      37,
      42,
      38,
      33,
      35,
      45,
      38,
      43,
      51,
      41,
      41,
      41,
      34,
      39,
      37,
      49,
      43,
      39,
      41,
      45,
      49,
      46,
      29,
      45,
      35,
      49,
      43,
      43,
      42,
      49,
      41,
      36,
      37,
      34,
      31,
      39,
      39,
      49,
      43,
      45,
      39,
      45,
      37,
      41,
      45,
      38,
      43,
      49,
      47,
      41,
      43,
      43,
      39,
      41,
      43,
      47,
      43,
      49,
      45,
      45,
      43,
      37,
      49,
      35,
      45,
      41,
      30,
      41,
      50,
      41,
      47,
      37,
      49,
      25,
      35,
      37,
      35,
      43,
      39,
      39,
      33,
      43,
      41,
      43,
      37,
      49,
      29,
      47,
      41,
      43,
      44,
      33,
      43,
      43,
      39,
      41,
      45,
      37,
      43,
      46,
      45,
      33,
      43,
      43,
      39,
      38,
      37,
      41,
      27,
      35,
      39,
      37,
      37,
      43,
      35,
      41,
      39,
      35,
      37,
      43,
      37,
      41,
      40,
      40,
      33,
      40,
      41,
      39,
      45,
      43,
      34,
      37,
      39,
      43,
      37,
      37,
      49,
      33,
      42,
      49,
      39,
      35,
      39,
      33,
      35,
      39,
      43,
      45,
      39,
      35,
      38,
      41,
      31,
      41,
      41,
      33,
      39,
      43,
      35,
      41,
      40,
      39,
      45,
      39,
      41,
      43,
      37,
      39,
      33,
      43,
      47,
      47,
      45,
      32,
      41,
      45,
      25,
      27,
      41,
      37,
      41,
      45,
      45,
      43,
      47,
      27,
      29,
      41,
      43,
      43,
      37,
      39,
      41,
      31,
      43,
      45,
      47,
      49,
      47,
      39,
      44,
      29,
      47,
      45,
      51,
      35,
      38,
      37,
      45,
      43,
      43,
      39,
      49,
      31,
      29,
      35,
      34,
      43,
      43,
      37,
      37,
      35,
      47,
      26,
      39,
      35,
      39,
      45,
      51,
      39,
      37,
      36,
      35,
      35,
      43,
      37,
      30,
      45,
      39,
      31,
      39,
      39,
      34,
      49,
      34,
      43,
      35,
      47,
      42,
      43,
      39,
      41,
      39,
      42,
      41,
      42,
      37,
      41,
      39,
      39,
      41,
      36,
      41,
      41,
      45,
      47,
      33,
      43,
      47,
      47,
      47,
      38,
      37,
      39,
      31,
      37,
      29,
      49,
      37,
      41,
      45,
      33,
      43,
      29,
      46,
      39,
      39,
      46,
      33,
      33,
      43,
      37,
      41,
      49,
      47,
      45,
      48,
      45,
      31,
      43,
      37,
      47,
      43,
      45,
      39,
      39,
      37,
      43,
      41,
      45,
      43,
      35,
      33,
      29,
      37,
      37,
      30,
      49,
      51,
      33,
      33,
      46,
      37,
      39,
      41,
      47,
      42,
      39,
      45,
      43,
      47,
      49,
      31,
      43,
      35,
      39,
      45,
      45,
      43,
      37,
      43,
      37,
      43,
      47,
      47,
      47,
      45,
      47,
      43,
      35,
      43,
      39,
      41,
      43,
      37,
      42,
      45,
      39,
      49,
      33,
      37,
      45,
      47,
      43,
      38,
      47,
      51,
      41,
      43,
      41,
      39,
      37,
      27,
      36,
      41,
      23,
      48,
      41,
      35,
      33,
      41,
      41,
      41,
      39,
      37,
      41,
      37,
      45,
      39,
      33,
      38,
      41,
      39,
      38,
      33,
      41,
      35,
      27,
      41,
      41,
      33,
      39,
      43,
      43,
      43,
      39,
      39,
      41,
      43,
      49,
      39,
      49,
      41,
      45,
      37,
      37,
      33,
      39,
      37,
      39,
      33,
      38,
      25,
      47,
      41,
      49,
      43,
      37,
      43,
      43,
      41,
      37,
      35,
      45,
      33,
      39,
      43,
      49,
      47,
      39,
      49,
      35,
      43,
      33,
      35,
      40,
      41,
      38,
      45,
      37,
      41,
      28,
      31,
      36,
      47,
      47,
      41,
      43,
      45,
      41,
      49,
      48,
      37,
      41,
      44,
      41,
      40,
      39,
      41,
      43,
      49,
      43,
      43,
      43,
      39,
      39,
      51,
      28,
      25,
      45,
      37,
      43,
      37,
      33,
      41,
      31,
      39,
      47,
      33,
      45,
      43,
      41,
      33,
      35,
      39,
      45,
      37,
      51,
      45,
      43,
      39,
      43,
      49,
      37,
      41,
      39,
      39,
      30,
      51,
      45,
      39,
      42,
      47,
      29,
      43,
      37,
      37,
      27,
      36,
      39,
      49,
      41,
      35,
      43,
      33,
      43,
      37,
      45,
      29,
      37,
      39,
      43,
      37,
      41,
      43,
      35,
      39,
      43,
      39,
      33,
      43,
      45,
      35,
      39,
      39,
      45,
      37,
      41,
      37,
      45,
      43,
      45,
      31,
      49,
      45,
      39,
      35,
      35,
      45,
      39,
      44,
      37,
      31,
      45,
      43,
      45,
      47,
      41,
      40,
      37,
      45,
      47,
      39,
      41,
      45,
      49,
      31,
      41,
      39,
      39,
      44,
      41,
      41,
      37,
      43,
      39,
      37,
      41,
      37,
      43,
      37,
      37,
      39,
      37,
      41,
      45
    ]
  }
}