{
  "classification_report": {
    "anger": {
      "precision": 0.20833333333333334,
      "recall": 0.3448275862068966,
      "f1-score": 0.2597402597402597,
      "support": 29.0
    },
    "neutral": {
      "precision": 0.5343915343915344,
      "recall": 0.2885714285714286,
      "f1-score": 0.3747680890538033,
      "support": 350.0
    },
    "approval": {
      "precision": 0.23214285714285715,
      "recall": 0.2549019607843137,
      "f1-score": 0.24299065420560748,
      "support": 51.0
    },
    "joy": {
      "precision": 0.23529411764705882,
      "recall": 0.2,
      "f1-score": 0.21621621621621623,
      "support": 20.0
    },
    "fear": {
      "precision": 0.38461538461538464,
      "recall": 0.35714285714285715,
      "f1-score": 0.37037037037037035,
      "support": 14.0
    },
    "disgust": {
      "precision": 0.3333333333333333,
      "recall": 0.4117647058823529,
      "f1-score": 0.3684210526315789,
      "support": 17.0
    },
    "desire": {
      "precision": 0.16666666666666666,
      "recall": 0.08333333333333333,
      "f1-score": 0.1111111111111111,
      "support": 12.0
    },
    "relief": {
      "precision": 0.3333333333333333,
      "recall": 0.5,
      "f1-score": 0.4,
      "support": 2.0
    },
    "admiration": {
      "precision": 0.4318181818181818,
      "recall": 0.5,
      "f1-score": 0.4634146341463415,
      "support": 76.0
    },
    "remorse": {
      "precision": 0.5,
      "recall": 0.2,
      "f1-score": 0.2857142857142857,
      "support": 10.0
    },
    "amusement": {
      "precision": 0.3442622950819672,
      "recall": 0.5121951219512195,
      "f1-score": 0.4117647058823529,
      "support": 41.0
    },
    "disapproval": {
      "precision": 0.14925373134328357,
      "recall": 0.23809523809523808,
      "f1-score": 0.1834862385321101,
      "support": 42.0
    },
    "caring": {
      "precision": 0.19047619047619047,
      "recall": 0.21052631578947367,
      "f1-score": 0.2,
      "support": 19.0
    },
    "grief": {
      "precision": 0.0,
      "recall": 0.0,
      "f1-score": 0.0,
      "support": 0.0
    },
    "nervousness": {
      "precision": 1.0,
      "recall": 0.3333333333333333,
      "f1-score": 0.5,
      "support": 3.0
    },
    "embarrassment": {
      "precision": 0.125,
      "recall": 0.2,
      "f1-score": 0.15384615384615385,
      "support": 5.0
    },
    "gratitude": {
      "precision": 0.775,
      "recall": 0.543859649122807,
      "f1-score": 0.6391752577319587,
      "support": 57.0
    },
    "surprise": {
      "precision": 0.2727272727272727,
      "recall": 0.15789473684210525,
      "f1-score": 0.2,
      "support": 19.0
    },
    "pride": {
      "precision": 0.0,
      "recall": 0.0,
      "f1-score": 0.0,
      "support": 2.0
    },
    "sadness": {
      "precision": 0.34375,
      "recall": 0.5,
      "f1-score": 0.4074074074074074,
      "support": 22.0
    },
    "curiosity": {
      "precision": 0.2608695652173913,
      "recall": 0.15789473684210525,
      "f1-score": 0.19672131147540983,
      "support": 38.0
    },
    "love": {
      "precision": 0.3137254901960784,
      "recall": 0.45714285714285713,
      "f1-score": 0.37209302325581395,
      "support": 35.0
    },
    "disappointment": {
      "precision": 0.11764705882352941,
      "recall": 0.10526315789473684,
      "f1-score": 0.1111111111111111,
      "support": 19.0
    },
    "confusion": {
      "precision": 0.125,
      "recall": 0.14285714285714285,
      "f1-score": 0.13333333333333333,
      "support": 21.0
    },
    "realization": {
      "precision": 0.1,
      "recall": 0.10526315789473684,
      "f1-score": 0.10256410256410256,
      "support": 19.0
    },
    "annoyance": {
      "precision": 0.24074074074074073,
      "recall": 0.30952380952380953,
      "f1-score": 0.2708333333333333,
      "support": 42.0
    },
    "excitement": {
      "precision": 0.26666666666666666,
      "recall": 0.3333333333333333,
      "f1-score": 0.2962962962962963,
      "support": 12.0
    },
    "optimism": {
      "precision": 0.3157894736842105,
      "recall": 0.2608695652173913,
      "f1-score": 0.2857142857142857,
      "support": 23.0
    },
    "micro avg": {
      "precision": 0.3468715697036224,
      "recall": 0.316,
      "f1-score": 0.33071690214547356,
      "support": 1000.0
    },
    "macro avg": {
      "precision": 0.29645847240139334,
      "recall": 0.27530692956290975,
      "f1-score": 0.26989618691690154,
      "support": 1000.0
    },
    "weighted avg": {
      "precision": 0.39393477768132407,
      "recall": 0.316,
      "f1-score": 0.33579091507490194,
      "support": 1000.0
    }
  },
  "accuracy": 0.316,
  "confusion_matrix": [
    [
      10,
      4,
      0,
      0,
      0,
      2,
      0,
      0,
      0,
      0,
      1,
      4,
      0,
      0,
      0,
      1,
      0,
      0,
      0,
      0,
      0,
      0,
      1,
      0,
      2,
      2,
      0,
      0
    ],
    [
      16,
      101,
      25,
      6,
      3,
      5,
      3,
      1,
      24,
      0,
      15,
      26,
      6,
      0,
      0,
      3,
      3,
      2,
      1,
      5,
      10,
      13,
      1,
      11,
      8,
      28,
      2,
      4
    ],
    [
      1,
      9,
      13,
      1,
      0,
      0,
      0,
      0,
      7,
      0,
      3,
      2,
      2,
      0,
      0,
      0,
      0,
      0,
      0,
      1,
      1,
      3,
      1,
      0,
      1,
      1,
      1,
      0
    ],
    [
      0,
      0,
      1,
      4,
      0,
      0,
      0,
      0,
      5,
      0,
      2,
      0,
      0,
      0,
      0,
      0,
      0,
      0,
      0,
      0,
      0,
      2,
      0,
      0,
      1,
      0,
      3,
      0
    ],
    [
      0,
      1,
      0,
      0,
      5,
      0,
      0,
      0,
      0,
      0,
      0,
      1,
      2,
      0,
      0,
      0,
      0,
      0,
      0,
      1,
      0,
      0,
      0,
      1,
      0,
      0,
      0,
      0
    ],
    [
      2,
      0,
      0,
      0,
      0,
      7,
      0,
      0,
      0,
      0,
      0,
      1,
      0,
      0,
      0,
      0,
      0,
      0,
      0,
      1,
      0,
      0,
      2,
      1,
      0,
      2,
      0,
      0
    ],
    [
      0,
      1,
      0,
      0,
      0,
      0,
      1,
      0,
      0,
      1,
      1,
      1,
      0,
      0,
      0,
      1,
      0,
      0,
      0,
      0,
      0,
      2,
      0,
      0,
      0,
      0,
      0,
      0
    ],
    [
      0,
      0,
      0,
      0,
      0,
      0,
      0,
      1,
      0,
      0,
      0,
      0,
      0,
      0,
      0,
      0,
      1,
      0,
      0,
      0,
      0,
      0,
      0,
      0,
      0,
      0,
      0,
      0
    ],
    [
      0,
      5,
      5,
      3,
      0,
      1,
      0,
      0,
      38,
      0,
      1,
      1,
      2,
      0,
      0,
      0,
      2,
      0,
      1,
      0,
      1,
      8,
      1,
      0,
      0,
      1,
      0,
      1
    ],
    [
      1,
      1,
      0,
      0,
      0,
      0,
      0,
      0,
      0,
      2,
      0,
      1,
      0,
      0,
      0,
      0,
      2,
      0,
      0,
      1,
      0,
      0,
      0,
      0,
      0,
      0,
      0,
      0
    ],
    [
      2,
      5,
      2,
      0,
      0,
      1,
      0,
      0,
      1,
      0,
      21,
      2,
      0,
      0,
      0,
      0,
      0,
      1,
      0,
      0,
      2,
      0,
      0,
      0,
      0,
      1,
      1,
      2
    ],
    [
      2,
      13,
      0,
      0,
      1,
      2,
      0,
      0,
      0,
      0,
      2,
      10,
      0,
      0,
      0,
      1,
      0,
      1,
      0,
      0,
      0,
      1,
      2,
      1,
      0,
      1,
      1,
      0
    ],
    [
      1,
      4,
      0,
      0,
      0,
      0,
      0,
      0,
      0,
      0,
      0,
      1,
      4,
      0,
      0,
      0,
      1,
      0,
      0,
      0,
      0,
      2,
      0,
      1,
      1,
      1,
      0,
      0
    ],
    [
      0,
      0,
      0,
      0,
      0,
      0,
      0,
      0,
      0,
      0,
      0,
      0,
      0,
      0,
      0,
      0,
      0,
      0,
      0,
      0,
      0,
      0,
      0,
      0,
      0,
      0,
      0,
      0
    ],
    [
      0,
      0,
      0,
      0,
      0,
      0,
      0,
      0,
      0,
      0,
      0,
      0,
      0,
      0,
      1,
      0,
      0,
      0,
      0,
      0,
      0,
      0,
      0,
      0,
      0,
      0,
      0,
      0
    ],
    [
      0,
      0,
      0,
      0,
      0,
      0,
      0,
      0,
      0,
      0,
      0,
      0,
      0,
      0,
      0,
      1,
      0,
      2,
      0,
      1,
      0,
      0,
      0,
      0,
      0,
      0,
      0,
      0
    ],
    [
      1,
      4,
      2,
      0,
      0,
      0,
      1,
      0,
      2,
      0,
      2,
      0,
      0,
      0,
      0,
      0,
      31,
      0,
      0,
      2,
      0,
      1,
      1,
      1,
      0,
      1,
      1,
      3
    ],
    [
      0,
      3,
      1,
      0,
      0,
      1,
      0,
      0,
      4,
      0,
      2,
      1,
      0,
      0,
      0,
      0,
      0,
      3,
      0,
      0,
      2,
      0,
      0,
      0,
      1,
      0,
      0,
      0
    ],
    [
      0,
      0,
      0,
      0,
      0,
      0,
      0,
      0,
      0,
      0,
      0,
      1,
      0,
      0,
      0,
      0,
      0,
      0,
      0,
      0,
      0,
      0,
      0,
      0,
      0,
      0,
      0,
      0
    ],
    [
      1,
      3,
      0,
      1,
      0,
      0,
      0,
      0,
      0,
      0,
      0,
      3,
      1,
      0,
      0,
      0,
      0,
      0,
      0,
      11,
      0,
      0,
      0,
      1,
      1,
      0,
      0,
      0
    ],
    [
      1,
      10,
      2,
      0,
      0,
      0,
      0,
      0,
      0,
      0,
      2,
      4,
      1,
      0,
      0,
      0,
      0,
      0,
      0,
      0,
      6,
      0,
      2,
      3,
      1,
      1,
      0,
      1
    ],
    [
      0,
      0,
      0,
      1,
      0,
      1,
      0,
      1,
      5,
      0,
      2,
      0,
      0,
      0,
      0,
      0,
      0,
      0,
      0,
      2,
      0,
      16,
      1,
      0,
      0,
      0,
      2,
      1
    ],
    [
      2,
      2,
      0,
      0,
      0,
      0,
      0,
      0,
      0,
      0,
      1,
      3,
      1,
      0,
      0,
      0,
      0,
      0,
      0,
      4,
      0,
      0,
      2,
      0,
      1,
      1,
      0,
      0
    ],
    [
      1,
      11,
      1,
      0,
      0,
      0,
      0,
      0,
      0,
      0,
      1,
      1,
      0,
      0,
      0,
      0,
      0,
      0,
      0,
      0,
      1,
      0,
      0,
      3,
      0,
      0,
      0,
      0
    ],
    [
      2,
      5,
      1,
      0,
      1,
      0,
      0,
      0,
      0,
      0,
      0,
      0,
      0,
      0,
      0,
      1,
      0,
      1,
      0,
      1,
      0,
      2,
      0,
      0,
      2,
      0,
      0,
      0
    ],
    [
      5,
      4,
      2,
      0,
      3,
      1,
      0,
      0,
      0,
      0,
      3,
      3,
      1,
      0,
      0,
      0,
      0,
      0,
      0,
      1,
      0,
      0,
      2,
      1,
      0,
      13,
      0,
      0
    ],
    [
      0,
      1,
      0,
      0,
      0,
      0,
      0,
      0,
      1,
      0,
      2,
      0,
      0,
      0,
      0,
      0,
      0,
      1,
      0,
      0,
      0,
      1,
      0,
      0,
      1,
      0,
      4,
      1
    ],
    [
      0,
      2,
      1,
      1,
      0,
      0,
      1,
      0,
      1,
      1,
      0,
      1,
      1,
      0,
      0,
      0,
      0,
      0,
      0,
      1,
      0,
      0,
      1,
      0,
      0,
      1,
      0,
      6
    ]
  ],
  "labels": [
    "anger",
    "neutral",
    "approval",
    "joy",
    "fear",
    "disgust",
    "desire",
    "relief",
    "admiration",
    "remorse",
    "amusement",
    "disapproval",
    "caring",
    "grief",
    "nervousness",
    "embarrassment",
    "gratitude",
    "surprise",
    "pride",
    "sadness",
    "curiosity",
    "love",
    "disappointment",
    "confusion",
    "realization",
    "annoyance",
    "excitement",
    "optimism"
  ]
}